asyncpg_datalayer/__init__.py
asyncpg_datalayer/base_repository.py
asyncpg_datalayer/base_table.py
asyncpg_datalayer/cli/__init__.py
asyncpg_datalayer/cli/main.py
asyncpg_datalayer/codegen/.gitignore
asyncpg_datalayer/codegen/README.md
asyncpg_datalayer/codegen/__init__.py
asyncpg_datalayer/codegen/main.py
asyncpg_datalayer/codegen/metadata.py
asyncpg_datalayer/codegen/metadata.sql
asyncpg_datalayer/codegen/templates/facade.tmpl
asyncpg_datalayer/codegen/templates/repository.tmpl
asyncpg_datalayer/criteria.py
asyncpg_datalayer/db.py
asyncpg_datalayer/db_factory.py
asyncpg_datalayer/errors.py
asyncpg_datalayer/migrationtool/README.md
asyncpg_datalayer/migrationtool/__init__.py
asyncpg_datalayer/migrationtool/main.py
asyncpg_datalayer/pagination.py
asyncpg_datalayer/pagination_and_sorting.py
asyncpg_datalayer/scrolling.py
asyncpg_datalayer/types.py
asyncpg_datalayer-0.0.3.dist-info/METADATA
asyncpg_datalayer-0.0.3.dist-info/WHEEL
asyncpg_datalayer-0.0.3.dist-info/entry_points.txt
asyncpg_datalayer-0.0.3.dist-info/licenses/LICENSE
asyncpg_datalayer-0.0.3.dist-info/RECORD
